oireachtas_data/__init__.py
oireachtas_data/constants.py
oireachtas_data/log.py
oireachtas_data/utils.py
oireachtas_data/bin/__init__.py
oireachtas_data/bin/analyse.py
oireachtas_data/bin/load_debates.py
oireachtas_data/bin/pull_debates.py
oireachtas_data/bin/pull_members.py
oireachtas_data/models/__init__.py
oireachtas_data/models/debate.py
oireachtas_data/models/debate_section.py
oireachtas_data/models/member.py
oireachtas_data/models/new_pdf.py
oireachtas_data/models/old_pdf.py
oireachtas_data/models/para.py
oireachtas_data/models/pdf.py
oireachtas_data/models/speech.py
oireachtas_data-0.1.19.dist-info/LICENSE
oireachtas_data-0.1.19.dist-info/METADATA
oireachtas_data-0.1.19.dist-info/WHEEL
oireachtas_data-0.1.19.dist-info/entry_points.txt
oireachtas_data-0.1.19.dist-info/top_level.txt
oireachtas_data-0.1.19.dist-info/RECORD
