Metadata-Version: 2.1
Name: oireachtas-data
Version: 0.1.19
Summary: Oireachtas debate data
Home-page: https://github.com/RobertLucey/oireachtas-data
Author: Robert Lucey
Requires-Python: >=3.6
License-File: LICENSE
Requires-Dist: ujson
Requires-Dist: requests
Requires-Dist: cached-property
Requires-Dist: bs4
Requires-Dist: nltk
Requires-Dist: pdftotext
Requires-Dist: transformers
Requires-Dist: unidecode
Requires-Dist: edlib
